minio_cache/__init__.py
minio_flask_cache-0.0.3.dist-info/licenses/LICENCE.md
minio_flask_cache-0.0.3.dist-info/METADATA
minio_flask_cache-0.0.3.dist-info/WHEEL
minio_flask_cache-0.0.3.dist-info/top_level.txt
minio_flask_cache-0.0.3.dist-info/RECORD
