Metadata-Version: 2.4
Name: minio-flask-cache
Version: 0.0.3
Summary: A custom cache backend for Flask-Caching based on Minio. Usable for applications like Superset as a cache backend out of the box.
Author-email: Grégoire GAILLY <greggailly@yahoo.fr>
Project-URL: Homepage, https://github.com/greggailly/minio-flask-cache
Keywords: flask,cache,minio
Classifier: License :: OSI Approved :: MIT License
Classifier: Programming Language :: Python
Classifier: Programming Language :: Python :: 3
Requires-Python: >=3.7
License-File: LICENCE.md
Requires-Dist: flask-caching>=2.3.0
Requires-Dist: minio>=7.2.0
Dynamic: license-file
